asof/__init__.py
asof/__main__.py
asof/canonical_names.py
asof/conda.py
asof/db.py
asof/package_match.py
asof/pypi.py
asof-0.1.1a0.dist-info/METADATA
asof-0.1.1a0.dist-info/WHEEL
asof-0.1.1a0.dist-info/entry_points.txt
asof-0.1.1a0.dist-info/RECORD
