Metadata-Version: 2.4
Name: asof
Version: 0.1.1a0
Project-URL: Homepage, https://github.com/maxkapur/asof.py
Project-URL: Documentation, https://github.com/maxkapur/asof.py
Project-URL: Repository, https://github.com/maxkapur/asof.py.git
Project-URL: Bug Tracker, https://github.com/maxkapur/asof.py/issues
Author-email: Max Kapur <git@maxkapur.com>
Maintainer-email: Max Kapur <git@maxkapur.com>
License-Expression: MIT
Requires-Python: ~=3.12
Requires-Dist: packaging~=25.0
Requires-Dist: platformdirs~=4.5
Requires-Dist: requests~=2.32
Requires-Dist: rich~=14.0
Provides-Extra: dev
Requires-Dist: mypy; extra == 'dev'
Requires-Dist: pytest; extra == 'dev'
Requires-Dist: pytest-mypy; extra == 'dev'
Requires-Dist: pytest-ruff; extra == 'dev'
Requires-Dist: ruff; extra == 'dev'
Requires-Dist: types-requests; extra == 'dev'
